autobigsst/engine/__init__.py
autobigsst/engine/data/__init__.py
autobigsst/engine/data/local/__init__.py
autobigsst/engine/data/local/csv.py
autobigsst/engine/data/local/fasta.py
autobigsst/engine/data/remote/__init__.py
autobigsst/engine/data/remote/databases/bigsdb.py
autobigsst/engine/data/structures/__init__.py
autobigsst/engine/data/structures/genomics.py
autobigsst/engine/data/structures/mlst.py
autobigsst/engine/exceptions/database.py
autobigsst.engine-0.6.0.dist-info/LICENSE
autobigsst.engine-0.6.0.dist-info/METADATA
autobigsst.engine-0.6.0.dist-info/WHEEL
autobigsst.engine-0.6.0.dist-info/top_level.txt
autobigsst.engine-0.6.0.dist-info/RECORD
