Metadata-Version: 2.2
Name: autobigsst.engine
Version: 0.6.0
Summary: A library to rapidly fetch fetch MLST profiles given sequences for various diseases.
Project-URL: Repository, https://github.com/RealYHD/autobigsst.engine.git
Project-URL: Issues, https://github.com/RealYHD/autobigsst.engine/issues
Requires-Python: >=3.11
License-File: LICENSE
Requires-Dist: biopython
Requires-Dist: aiohttp[speedups]
